nex_face/__init__.py
nex_face/embedding_clustering/__init__.py
nex_face/embedding_clustering/embedding_clustering.py
nex_face/embedding_extraction/__init__.py
nex_face/embedding_extraction/base_embedding_extractor.py
nex_face/embedding_extraction/embedding_extractor.py
nex_face/face_extraction/__init__.py
nex_face/face_extraction/face_extractor.py
nex_face/face_recognition/__init__.py
nex_face/face_recognition/face_recognizer.py
nex_face/models/__init__.py
nex_face/models/face_detection_result_model.py
nex_face/models/abc/__init__.py
nex_face/models/abc/base_ai_model.py
nex_face/resources/__init__.py
nex_face/resources/face_detection_yunet_2023mar.onnx
nex_face/resources/facenet_keras_2024.h5
nex_face/utils/__init__.py
nex_face/utils/utils.py
nexface-0.0.9.dist-info/METADATA
nexface-0.0.9.dist-info/WHEEL
nexface-0.0.9.dist-info/top_level.txt
nexface-0.0.9.dist-info/RECORD
