Metadata-Version: 2.1
Name: nexface
Version: 0.0.9
Summary: A face recognition and embedding extraction library
Home-page: https://github.com/fatihdagdeviren/NexFace
Author: Fatih Dagdeviren
Author-email: fatihdagdeviren21@gmail.com
Classifier: Programming Language :: Python :: 3
Classifier: License :: OSI Approved :: MIT License
Classifier: Operating System :: OS Independent
Requires-Python: >=3.6
Requires-Dist: numpy
Requires-Dist: opencv-python==4.12.0.88
Requires-Dist: opencv-contrib-python==4.12.0.88
Requires-Dist: scikit-learn==1.7.0
Requires-Dist: onnx==1.18.0
Requires-Dist: hdbscan==0.8.40
Requires-Dist: typing-extensions
Requires-Dist: tensorflow==2.19.0
